[{"date": "20150601", "max": "  161", "gmld": "  127", "min": "   61"}, {"date": "20150602", "max": "  177", "gmld": "  148", "min": "  111"}, {"date": "20150603", "max": "  177", "gmld": "  138", "min": "   63"}, {"date": "20150604", "max": "  220", "gmld": "  156", "min": "   46"}, {"date": "20150605", "max": "  318", "gmld": "  214", "min": "   95"}, {"date": "20150606", "max": "  189", "gmld": "  156", "min": "   85"}, {"date": "20150607", "max": "  189", "gmld": "  139", "min": "   71"}, {"date": "20150608", "max": "  172", "gmld": "  125", "min": "   79"}, {"date": "20150609", "max": "  150", "gmld": "  116", "min": "   75"}, {"date": "20150610", "max": "  208", "gmld": "  154", "min": "   89"}, {"date": "20150611", "max": "  240", "gmld": "  179", "min": "   93"}, {"date": "20150612", "max": "  274", "gmld": "  216", "min": "  128"}, {"date": "20150613", "max": "  213", "gmld": "  175", "min": "  141"}, {"date": "20150614", "max": "  195", "gmld": "  153", "min": "  123"}, {"date": "20150615", "max": "  175", "gmld": "  133", "min": "   76"}, {"date": "20150616", "max": "  177", "gmld": "  114", "min": "   45"}, {"date": "20150617", "max": "  227", "gmld": "  160", "min": "   53"}, {"date": "20150618", "max": "  166", "gmld": "  143", "min": "  115"}, {"date": "20150619", "max": "  153", "gmld": "  127", "min": "  103"}, {"date": "20150620", "max": "  163", "gmld": "  130", "min": "   97"}, {"date": "20150621", "max": "  185", "gmld": "  144", "min": "  121"}, {"date": "20150622", "max": "  153", "gmld": "  127", "min": "   76"}, {"date": "20150623", "max": "  151", "gmld": "  126", "min": "   94"}, {"date": "20150624", "max": "  215", "gmld": "  158", "min": "  117"}, {"date": "20150625", "max": "  240", "gmld": "  182", "min": "  114"}, {"date": "20150626", "max": "  250", "gmld": "  205", "min": "  134"}, {"date": "20150627", "max": "  218", "gmld": "  176", "min": "  103"}, {"date": "20150628", "max": "  232", "gmld": "  173", "min": "   88"}, {"date": "20150629", "max": "  242", "gmld": "  180", "min": "  112"}, {"date": "20150630", "max": "  273", "gmld": "  206", "min": "   97"}]